{"creator":"Koen","grouptitle":"Game #1","image":"logo.png","imagelocation":"main","maxterminals":"1","creationtime":1544126886,"qgroups":["games\/0511\/GeF"],"id":"0511","terminals":[{"text":"Wacht...","questiongroup":"GeF","question":"66","group":null,"activated":true,"inuse":false,"id":"17"},{"text":"Wacht...","activated":false,"inuse":false,"question":0,"questiongroup":0,"group":0,"id":"18"},{"text":"Wacht...","activated":false,"inuse":false,"question":"66","questiongroup":"GeF","group":0,"id":"fb"}]}